dynamic_config_qq/__init__.py
dynamic_config_qq/dynamic_config_client.py
dynamic_config_qq/dynamic_config_manager.py
dynamic_config_qq/exceptions.py
dynamic_config_qq-1.3.0.dist-info/licenses/LICENSE
dynamic_config_qq-1.3.0.dist-info/METADATA
dynamic_config_qq-1.3.0.dist-info/WHEEL
dynamic_config_qq-1.3.0.dist-info/top_level.txt
dynamic_config_qq-1.3.0.dist-info/RECORD
