Metadata-Version: 2.4
Name: dynamic_config_qq
Version: 1.3.0
Summary: 基于Redis Cluster的动态配置管理系统，采用主动拉取(Pull)+推送(Push)双模式更新策略，内置LRU本地缓存。
Home-page: https://github.com/MMMMMM1028/dynamic-config
Author: wzc
Author-email: wzc@xxx.com
Keywords: redis,gevent,dynamic_config_qq,pubsub,cluster
Classifier: Intended Audience :: Developers
Classifier: License :: OSI Approved :: MIT License
Classifier: Programming Language :: Python
Classifier: Programming Language :: Python :: 2
Classifier: Programming Language :: Python :: 2.7
Classifier: Programming Language :: Python :: 3
Classifier: Programming Language :: Python :: 3.7
Classifier: Programming Language :: Python :: 3.8
Requires-Python: >=2.7
License-File: LICENSE
Requires-Dist: redis<4.0.0,>=3.0.0
Requires-Dist: redis-py-cluster>=2.1.3
Requires-Dist: gevent>=23.3.1
Dynamic: author
Dynamic: author-email
Dynamic: classifier
Dynamic: description
Dynamic: description-content-type
Dynamic: home-page
Dynamic: keywords
Dynamic: license-file
Dynamic: requires-dist
Dynamic: requires-python
Dynamic: summary
